sqlalchemy_aio/__init__.py
sqlalchemy_aio/asyncio.py
sqlalchemy_aio/base.py
sqlalchemy_aio/exc.py
sqlalchemy_aio/strategy.py
sqlalchemy_aio/trio.py
tests/asyncio/__init__.py
tests/asyncio/test_connection.py
tests/asyncio/test_engine.py
tests/asyncio/test_result_proxy.py
tests/asyncio/test_worker.py
tests/trio/__init__.py
tests/trio/test_connection.py
tests/trio/test_engine.py
tests/trio/test_result_proxy.py
tests/trio/test_worker.py
sqlalchemy_aio-0.17.0.dist-info/LICENSE
sqlalchemy_aio-0.17.0.dist-info/METADATA
sqlalchemy_aio-0.17.0.dist-info/WHEEL
sqlalchemy_aio-0.17.0.dist-info/top_level.txt
sqlalchemy_aio-0.17.0.dist-info/RECORD
