Metadata-Version: 2.1
Name: sqlalchemy-aio
Version: 0.17.0
Summary: Async support for SQLAlchemy.
Home-page: https://github.com/RazerM/sqlalchemy_aio
Author: Frazer McLean
Author-email: frazer@frazermclean.co.uk
License: MIT
Platform: UNKNOWN
Classifier: Development Status :: 4 - Beta
Classifier: License :: OSI Approved :: MIT License
Classifier: Programming Language :: Python :: 3
Requires-Python: >=3.6
Provides-Extra: test-noextras
Provides-Extra: test
Provides-Extra: trio
License-File: LICENSE
